TokenizerChanger/__init__.py
TokenizerChanger/tokenizer_changer.py
tokenizerchanger-1.1.0.dist-info/LICENSE
tokenizerchanger-1.1.0.dist-info/METADATA
tokenizerchanger-1.1.0.dist-info/WHEEL
tokenizerchanger-1.1.0.dist-info/top_level.txt
tokenizerchanger-1.1.0.dist-info/RECORD
