Metadata-Version: 2.1
Name: tokenizerchanger
Version: 1.1.0
Summary: Library for manipulating the existing tokenizer.
Home-page: https://github.com/1kkiRen/Tokenizer-Changer
Author: 1kkiren
Author-email: 1kkiren@mail.ru
Project-URL: GitHub, https://github.com/1kkiRen/Tokenizer-Changer
Keywords: tokenizer deletion tokens
Classifier: Programming Language :: Python :: 3.10
Classifier: License :: OSI Approved :: Apache Software License
Classifier: Operating System :: OS Independent
Requires-Python: >=3.9
License-File: LICENSE
Requires-Dist: tokenizers >=0.21.0
Requires-Dist: tqdm >=4.66.4
Requires-Dist: transformers >=4.47.0
